{
"meta":{"test_sets":[],"test_metrics":[],"learn_metrics":[{"best_value":"Min","name":"RMSE"}],"launch_mode":"Train","parameters":"","iteration_count":100,"learn_sets":["learn"],"name":"experiment"},
"iterations":[
{"learn":[14.005006],"iteration":0,"passed_time":0.0008727473094,"remaining_time":0.08640198363},
{"learn":[13.14441192],"iteration":1,"passed_time":0.001583744581,"remaining_time":0.07760348447},
{"learn":[12.34258257],"iteration":2,"passed_time":0.002099709819,"remaining_time":0.06789061749},
{"learn":[11.64527793],"iteration":3,"passed_time":0.002521271998,"remaining_time":0.06051052796},
{"learn":[11.02766183],"iteration":4,"passed_time":0.003060654852,"remaining_time":0.05815244218},
{"learn":[10.43485794],"iteration":5,"passed_time":0.003594093276,"remaining_time":0.05630746132},
{"learn":[9.890641275],"iteration":6,"passed_time":0.004030912901,"remaining_time":0.05355355712},
{"learn":[9.492161212],"iteration":7,"passed_time":0.004471642453,"remaining_time":0.05142388821},
{"learn":[9.105082953],"iteration":8,"passed_time":0.00497250985,"remaining_time":0.0502775996},
{"learn":[8.674157135],"iteration":9,"passed_time":0.005425870885,"remaining_time":0.04883283797},
{"learn":[8.341743544],"iteration":10,"passed_time":0.005926908967,"remaining_time":0.04795408164},
{"learn":[8.049372916],"iteration":11,"passed_time":0.006445731267,"remaining_time":0.04726869596},
{"learn":[7.757318612],"iteration":12,"passed_time":0.006862411116,"remaining_time":0.0459253667},
{"learn":[7.522206899],"iteration":13,"passed_time":0.007271622242,"remaining_time":0.04466853663},
{"learn":[7.297756655],"iteration":14,"passed_time":0.00769389618,"remaining_time":0.04359874502},
{"learn":[7.088359431],"iteration":15,"passed_time":0.00816815861,"remaining_time":0.0428828327},
{"learn":[6.882113791],"iteration":16,"passed_time":0.008587013836,"remaining_time":0.04192483226},
{"learn":[6.704728832],"iteration":17,"passed_time":0.00899132311,"remaining_time":0.04096047195},
{"learn":[6.563881962],"iteration":18,"passed_time":0.009470025989,"remaining_time":0.04037221606},
{"learn":[6.418790279],"iteration":19,"passed_time":0.009870515823,"remaining_time":0.03948206329},
{"learn":[6.315756953],"iteration":20,"passed_time":0.0103632336,"remaining_time":0.03898549784},
{"learn":[6.210157751],"iteration":21,"passed_time":0.01080702045,"remaining_time":0.03831579978},
{"learn":[6.115058449],"iteration":22,"passed_time":0.01125650163,"remaining_time":0.03768480981},
{"learn":[6.014819884],"iteration":23,"passed_time":0.01170697474,"remaining_time":0.03707208667},
{"learn":[5.93117229],"iteration":24,"passed_time":0.01221513068,"remaining_time":0.03664539203},
{"learn":[5.844857622],"iteration":25,"passed_time":0.0127852801,"remaining_time":0.03638887412},
{"learn":[5.771145213],"iteration":26,"passed_time":0.01329952107,"remaining_time":0.03595796439},
{"learn":[5.704018229],"iteration":27,"passed_time":0.01385789138,"remaining_time":0.03563457784},
{"learn":[5.665806474],"iteration":28,"passed_time":0.0143802023,"remaining_time":0.03520670219},
{"learn":[5.616500369],"iteration":29,"passed_time":0.01492094826,"remaining_time":0.03481554595},
{"learn":[5.558023666],"iteration":30,"passed_time":0.01555855414,"remaining_time":0.03463033019},
{"learn":[5.510080976],"iteration":31,"passed_time":0.01606138693,"remaining_time":0.03413044722},
{"learn":[5.468747792],"iteration":32,"passed_time":0.01653492731,"remaining_time":0.03357091302},
{"learn":[5.429275534],"iteration":33,"passed_time":0.01700388663,"remaining_time":0.03300754464},
{"learn":[5.402117324],"iteration":34,"passed_time":0.01751445828,"remaining_time":0.03252685108},
{"learn":[5.367635151],"iteration":35,"passed_time":0.01802160224,"remaining_time":0.03203840398},
{"learn":[5.345181232],"iteration":36,"passed_time":0.01853458009,"remaining_time":0.03155887962},
{"learn":[5.319151269],"iteration":37,"passed_time":0.01903752948,"remaining_time":0.03106123231},
{"learn":[5.296134146],"iteration":38,"passed_time":0.01945548247,"remaining_time":0.03043037002},
{"learn":[5.269629003],"iteration":39,"passed_time":0.02000544542,"remaining_time":0.03000816814},
{"learn":[5.251147059],"iteration":40,"passed_time":0.02045173846,"remaining_time":0.02943055047},
{"learn":[5.248003302],"iteration":41,"passed_time":0.02067411809,"remaining_time":0.0285499726},
{"learn":[5.232376509],"iteration":42,"passed_time":0.02108479309,"remaining_time":0.02794960945},
{"learn":[5.213524255],"iteration":43,"passed_time":0.02154478974,"remaining_time":0.02742064149},
{"learn":[5.189691584],"iteration":44,"passed_time":0.02200740312,"remaining_time":0.02689793714},
{"learn":[5.166052198],"iteration":45,"passed_time":0.02254827993,"remaining_time":0.02646971991},
{"learn":[5.140406659],"iteration":46,"passed_time":0.02300614182,"remaining_time":0.0259430961},
{"learn":[5.118929684],"iteration":47,"passed_time":0.02351471854,"remaining_time":0.02547427841},
{"learn":[5.108792602],"iteration":48,"passed_time":0.02411224536,"remaining_time":0.02509641864},
{"learn":[5.098141225],"iteration":49,"passed_time":0.02468972236,"remaining_time":0.02468972236},
{"learn":[5.085926393],"iteration":50,"passed_time":0.02530429131,"remaining_time":0.02431196616},
{"learn":[5.067816804],"iteration":51,"passed_time":0.0260580242,"remaining_time":0.0240535608},
{"learn":[5.049834901],"iteration":52,"passed_time":0.02675002452,"remaining_time":0.02372171986},
{"learn":[5.03838627],"iteration":53,"passed_time":0.02746837048,"remaining_time":0.02339898226},
{"learn":[5.033534248],"iteration":54,"passed_time":0.02790017798,"remaining_time":0.02282741835},
{"learn":[5.023726885],"iteration":55,"passed_time":0.02850051201,"remaining_time":0.02239325943},
{"learn":[5.01290392],"iteration":56,"passed_time":0.02901188537,"remaining_time":0.02188615914},
{"learn":[5.005569127],"iteration":57,"passed_time":0.02948998703,"remaining_time":0.02135481819},
{"learn":[4.989969032],"iteration":58,"passed_time":0.02996594338,"remaining_time":0.02082379116},
{"learn":[4.976762446],"iteration":59,"passed_time":0.03068442969,"remaining_time":0.02045628646},
{"learn":[4.967222715],"iteration":60,"passed_time":0.03127112922,"remaining_time":0.01999301704},
{"learn":[4.954407599],"iteration":61,"passed_time":0.03176992228,"remaining_time":0.01947188785},
{"learn":[4.942125056],"iteration":62,"passed_time":0.03242071101,"remaining_time":0.01904073504},
{"learn":[4.930230716],"iteration":63,"passed_time":0.03290597009,"remaining_time":0.01850960818},
{"learn":[4.921695642],"iteration":64,"passed_time":0.03335278468,"remaining_time":0.01795919175},
{"learn":[4.906405625],"iteration":65,"passed_time":0.03380028043,"remaining_time":0.01741226568},
{"learn":[4.894330248],"iteration":66,"passed_time":0.03424079946,"remaining_time":0.01686487138},
{"learn":[4.88211557],"iteration":67,"passed_time":0.03468967863,"remaining_time":0.01632455465},
{"learn":[4.877946398],"iteration":68,"passed_time":0.03513743555,"remaining_time":0.01578638409},
{"learn":[4.863182126],"iteration":69,"passed_time":0.03558625484,"remaining_time":0.01525125207},
{"learn":[4.84646533],"iteration":70,"passed_time":0.03606952928,"remaining_time":0.01473262463},
{"learn":[4.838014752],"iteration":71,"passed_time":0.03653172161,"remaining_time":0.01420678063},
{"learn":[4.82981137],"iteration":72,"passed_time":0.03696828033,"remaining_time":0.01367319957},
{"learn":[4.817094767],"iteration":73,"passed_time":0.03739124598,"remaining_time":0.0131374648},
{"learn":[4.808314151],"iteration":74,"passed_time":0.03788677043,"remaining_time":0.01262892348},
{"learn":[4.796235023],"iteration":75,"passed_time":0.0383889917,"remaining_time":0.01212283948},
{"learn":[4.784434534],"iteration":76,"passed_time":0.03884176101,"remaining_time":0.01160208446},
{"learn":[4.774402487],"iteration":77,"passed_time":0.03932722085,"remaining_time":0.01109229306},
{"learn":[4.76731896],"iteration":78,"passed_time":0.03992098812,"remaining_time":0.01061190823},
{"learn":[4.75934113],"iteration":79,"passed_time":0.0404225678,"remaining_time":0.01010564195},
{"learn":[4.754106378],"iteration":80,"passed_time":0.04095153544,"remaining_time":0.009605915721},
{"learn":[4.744002932],"iteration":81,"passed_time":0.04148493377,"remaining_time":0.009106448876},
{"learn":[4.731700554],"iteration":82,"passed_time":0.04200535001,"remaining_time":0.008603505423},
{"learn":[4.723284153],"iteration":83,"passed_time":0.04267929544,"remaining_time":0.008129389608},
{"learn":[4.712232782],"iteration":84,"passed_time":0.04326857214,"remaining_time":0.007635630377},
{"learn":[4.703046867],"iteration":85,"passed_time":0.0438210674,"remaining_time":0.007133662134},
{"learn":[4.698601855],"iteration":86,"passed_time":0.04432498312,"remaining_time":0.006623273339},
{"learn":[4.692429407],"iteration":87,"passed_time":0.04497381332,"remaining_time":0.006132792725},
{"learn":[4.675027364],"iteration":88,"passed_time":0.04548155824,"remaining_time":0.005621316187},
{"learn":[4.662368584],"iteration":89,"passed_time":0.04624854363,"remaining_time":0.00513872707},
{"learn":[4.646206172],"iteration":90,"passed_time":0.04716825701,"remaining_time":0.004664992452},
{"learn":[4.641245848],"iteration":91,"passed_time":0.04777168315,"remaining_time":0.004154059405},
{"learn":[4.633900435],"iteration":92,"passed_time":0.04830171342,"remaining_time":0.003635612838},
{"learn":[4.624738236],"iteration":93,"passed_time":0.04880872627,"remaining_time":0.003115450613},
{"learn":[4.612798287],"iteration":94,"passed_time":0.04924853328,"remaining_time":0.002592028067},
{"learn":[4.605222001],"iteration":95,"passed_time":0.04970462052,"remaining_time":0.002071025855},
{"learn":[4.601725912],"iteration":96,"passed_time":0.05013058358,"remaining_time":0.00155043042},
{"learn":[4.59722371],"iteration":97,"passed_time":0.05061855938,"remaining_time":0.001033031824},
{"learn":[4.580235665],"iteration":98,"passed_time":0.0510790074,"remaining_time":0.0005159495697},
{"learn":[4.57591791],"iteration":99,"passed_time":0.05152214237,"remaining_time":0}
]}